setup.py
src/po_file_checker/__init__.py
src/po_file_checker/base.py
src/po_file_checker/check.py
src/po_file_checker.egg-info/PKG-INFO
src/po_file_checker.egg-info/SOURCES.txt
src/po_file_checker.egg-info/dependency_links.txt
src/po_file_checker.egg-info/requires.txt
src/po_file_checker.egg-info/top_level.txt
src/po_file_checker/management/__init__.py
src/po_file_checker/management/commands/__init__.py
src/po_file_checker/management/commands/check_po_files.py