Metadata-Version: 1.0
Name: po-file-checker
Version: 0.3
Summary: Check that po-files have no untranslated keys
Home-page: UNKNOWN
Author: UNKNOWN
Author-email: chapson@yandex-team.ru
License: UNKNOWN
Keywords: po-file,build-tools,sanity check
Platform: UNKNOWN
